magnus_extension_aws_secrets_manager/aws_secrets_manager.py
magnus_extension_aws_secrets_manager/integration.py
magnus_extension_aws_secrets_manager-0.1.0.dist-info/entry_points.txt
magnus_extension_aws_secrets_manager-0.1.0.dist-info/WHEEL
magnus_extension_aws_secrets_manager-0.1.0.dist-info/METADATA
magnus_extension_aws_secrets_manager-0.1.0.dist-info/RECORD
