Metadata-Version: 2.1
Name: magnus-extension-aws-secrets-manager
Version: 0.1.0
Summary: Description you want to give
Home-page: https://github.com/AstraZeneca/magnus-extensions/
License: Apache-2.0
Author: Vijay Vammi
Author-email: vijay.vammi@astrazeneca.com
Requires-Python: >=3.6.1,<4.0.0
Classifier: License :: OSI Approved :: Apache Software License
Classifier: Programming Language :: Python :: 3
Classifier: Programming Language :: Python :: 3.10
Classifier: Programming Language :: Python :: 3.7
Classifier: Programming Language :: Python :: 3.8
Classifier: Programming Language :: Python :: 3.9
Requires-Dist: magnus
Requires-Dist: magnus_extension_aws_config
Project-URL: Documentation, https://astrazeneca.github.io/magnus-extensions/
Project-URL: Repository, https://github.com/AstraZeneca/magnus-extensions/
